gfycat/__init__.py
gfycat/client.py
gfycat/constants.py
gfycat/error.py
gfycat-0.2.2.dist-info/LICENSE
gfycat-0.2.2.dist-info/METADATA
gfycat-0.2.2.dist-info/WHEEL
gfycat-0.2.2.dist-info/top_level.txt
gfycat-0.2.2.dist-info/RECORD
