Metadata-Version: 2.1
Name: gfycat
Version: 0.2.2
Summary: A Python client for the Gfycat API
Home-page: https://github.com/ankeshanand/py-gfycat/
Author: Ankesh Anand
Author-email: ankeshanand1994@gmail.com
License: MIT
Keywords: api,gfycat,client
Platform: UNKNOWN
Classifier: Development Status :: 3 - Alpha
Classifier: Intended Audience :: Developers
Classifier: License :: OSI Approved :: MIT License
Classifier: Programming Language :: Python :: 2.7
Classifier: Programming Language :: Python :: 3
Classifier: Programming Language :: Python :: 3.2
Classifier: Programming Language :: Python :: 3.3
Classifier: Programming Language :: Python :: 3.4
Classifier: Programming Language :: Python :: 3.5
Classifier: Programming Language :: Python :: 3.6
Classifier: Programming Language :: Python :: 3.7
Requires-Dist: requests (>=2.7.0)
